beekeeper/vector_stores/elasticsearch/__init__.py
beekeeper/vector_stores/elasticsearch/base.py
beekeeper_vector_stores_elasticsearch-1.0.1.dist-info/METADATA
beekeeper_vector_stores_elasticsearch-1.0.1.dist-info/WHEEL
beekeeper_vector_stores_elasticsearch-1.0.1.dist-info/RECORD
